{
    "M1": [
        {
            "stt": "1",
            "ma": "M0201",
            "ten": "Cần cẩu bánh hơi 16T",
            "donvi": "ca",
            "haophi": "0,093",
            "giagoc": "2181255",
            "gia": "",
            "haophikhac": "2"
        },
        {
            "stt": "2",
            "ma": "M0561",
            "ten": "Máy cắt cáp 10kW",
            "donvi": "ca",
            "haophi": "2,8",
            "giagoc": "281925",
            "gia": "",
            "haophikhac": "2"
        },
        {
            "stt": "3",
            "ma": "M2015",
            "ten": "Hệ kích thủy lực 25T",
            "donvi": "ca",
            "haophi": "0,28",
            "giagoc": "409168",
            "gia": "",
            "haophikhac": "2"
        },
        {
            "stt": "4",
            "ma": "ZM999",
            "ten": "Máy khác",
            "donvi": "%",
            "haophi": "2",
            "giagoc": "11068,1",
            "gia": "",
            "haophikhac": "0"
        }
    ],
    "M2": [
        {
            "stt": "1",
            "ma": "M0974",
            "ten": "Máy hút chân không",
            "donvi": "ca",
            "haophi": "0,65",
            "giagoc": "3499",
            "gia": "",
            "haophikhac": "5"
        },
        {
            "stt": "2",
            "ma": "M2007",
            "ten": "Máy cắt, mài mẫu vật liệu",
            "donvi": "ca",
            "haophi": "0,3",
            "giagoc": "14850",
            "gia": "",
            "haophikhac": "5"
        },
        {
            "stt": "3",
            "ma": "M0173",
            "ten": "Cân kỹ thuật",
            "donvi": "ca",
            "haophi": "0,24",
            "giagoc": "6521",
            "gia": "",
            "haophikhac": "5"
        },
        {
            "stt": "4",
            "ma": "M7725",
            "ten": "Tủ sấy",
            "donvi": "ca",
            "haophi": "3,3",
            "giagoc": "11348",
            "gia": "",
            "haophikhac": "5"
        },
        {
            "stt": "5",
            "ma": "M0968",
            "ten": "Máy hút ẩm",
            "donvi": "ca",
            "haophi": "0,5",
            "giagoc": "9287",
            "gia": "",
            "haophikhac": "5"
        },
        {
            "stt": "6",
            "ma": "ZM999",
            "ten": "Máy khác",
            "donvi": "%",
            "haophi": "5",
            "giagoc": "503,9",
            "gia": "",
            "haophikhac": "0"
        }
    ],
    "M3": [
        {
            "stt": "1",
            "ma": "M1034",
            "ten": "Máy khoan bê tông 0,62kW",
            "donvi": "ca",
            "haophi": "0,15",
            "giagoc": "14872",
            "gia": "",
            "haophikhac": "0"
        }
    ]
}